lair/__init__.py
lair/project_generator.py
lair/run.py
lair/blueprints/__init__.py
lair/blueprints/json.py
lair/decorators/__init__.py
lair/decorators/crossdomain.py
lair/templates/MANIFEST.in.j2
lair/templates/Makefile.j2
lair/templates/README.rst.j2
lair/templates/_coveragerc.j2
lair/templates/_gitignore.j2
lair/templates/_travis.yml.j2
lair/templates/docs_Makefile.j2
lair/templates/docs_source_conf.py.j2
lair/templates/docs_source_index.rst.j2
lair/templates/requirements.txt.j2
lair/templates/setup.py.j2
lair/templates/test-requirements.txt.j2
lair/templates/tests_endpoints_test_main.py.j2
lair/templates/tox.ini.j2
lair/templates/{module-name}___init__.py.j2
lair/templates/{module-name}_app.py.j2
lair/templates/{module-name}_database.py.j2
lair/templates/{module-name}_endpoints___init__.py.j2
lair/templates/{module-name}_endpoints_main.py.j2
lair/templates/{module-name}_models_example.py.j2
lair/templates/{module-name}_run.py.j2
lair/templates/{module-name}_settings.ini.j2
tests/__init__.py
tests/test_project_generator.py
tests/test_run.py
tests/blueprints/__init__.py
tests/blueprints/test_json.py
tests/decorators/__init__.py
tests/decorators/test_crossdomain.py
lair-1.1.0.dist-info/LICENSE
lair-1.1.0.dist-info/METADATA
lair-1.1.0.dist-info/WHEEL
lair-1.1.0.dist-info/entry_points.txt
lair-1.1.0.dist-info/top_level.txt
lair-1.1.0.dist-info/zip-safe
lair-1.1.0.dist-info/RECORD
